[
    {
        "id":1,
        "name": "Goku",
        "image": "http://media.japanpowered.com/images/goku.png"
    },
    {
        "id":2,
        "name": "Bulma",
        "image": "https://pngimage.net/wp-content/uploads/2018/05/bulma-png-8.png"
    },
    {
        "id":3,
        "name": "Master Roshi",
        "image": "https://vignette.wikia.nocookie.net/fictional-battle-omniverse/images/3/30/Master_Roshi_Dragon_Ball.png/revision/latest?cb=20160208025545"
    },
    {
        "id":4,
        "name": "Broly",
        "image": "https://i.pinimg.com/originals/98/39/1a/98391a7b8bd0bfd16d1bd68fb47df626.png"
    },
    {
        "id":5,
        "name": "Krillin",
        "image": "https://3.bp.blogspot.com/-eedF06cd2L8/WXvCV_ZwrMI/AAAAAAAAAZg/w6UkNyl5NycIBuMj5o_75tUEfOnsTqoDQCLcBGAs/s1600/krillin___dragonball_z__saiyan_saga__by_krillin888-d9p7qj4.png"
    },
    {
        "id":6,
        "name": "Tien",
        "image": "https://vignette.wikia.nocookie.net/deathbattlefanon/images/1/16/Tien.png/revision/latest?cb=20150409194538"
    },
    {
        "id":7,
        "name": "Piccolo",
        "image": "https://vignette.wikia.nocookie.net/fanfictioncharacters/images/e/e5/Piccolo.png/revision/latest?cb=20180203115506"
    },
    {
        "id":8,
        "name": "Gohan",
        "image": "https://ya-webdesign.com/images/gohan-transparent-2.png"
    },
    {
        "id":9,
        "name": "Vegeta",
        "image": "https://i.imgur.com/H6w9u7O.jpg"
    },
    {
        "id":10,
        "name": "Trunks",
        "image": "https://i.pinimg.com/originals/d8/e9/12/d8e912a9dd6f7f613f0aa998ac55197a.png"
    },
    {
        "id":11,
        "name": "Cell",
        "image": "https://i.pinimg.com/originals/2b/88/f7/2b88f7a4ea1d4ed7fc396dd6363f5c6f.png"
    },
    {
        "id":12,
        "name": "Goten",
        "image": "https://dbshop.fr/wp-content/uploads/2017/11/goten.png"
    }
]